helloworld.py
unrealai-0.0.6.dist-info/LICENSE
unrealai-0.0.6.dist-info/METADATA
unrealai-0.0.6.dist-info/WHEEL
unrealai-0.0.6.dist-info/top_level.txt
unrealai-0.0.6.dist-info/RECORD
