Metadata-Version: 2.1
Name: unrealai
Version: 0.0.6
Summary: Fixed testfile location
Home-page: https://github.com/nishgaba-ai/unrealai
Author: Nishchal Gaba
Author-email: nishgaba.ai@gmail.com
License: UNKNOWN
Platform: UNKNOWN
Classifier: Programming Language :: Python :: 3
Classifier: Programming Language :: Python :: 3.6
Classifier: Programming Language :: Python :: 3.7
Classifier: License :: OSI Approved :: GNU General Public License v2 or later (GPLv2+)
Classifier: Operating System :: OS Independent
